{"assets":{"9FEB16CCE631A41FF8DF9B2FBC2D9287":{"type":"texture","index":1,"assetRequest":{"type":"slide","state":"contents","slide":"none"},"url":{"native":"assets\/5C508FD4-567E-4161-89C9-D60EFF85FF30.pdf"},"width":1920,"height":1080},"67DAA57F27CAEFA2158408D0F5F1A880":{"type":"texture","index":0,"assetRequest":{"type":"slide","state":"contents","slide":"none"},"url":{"native":"assets\/5C508FD4-567E-4161-89C9-D60EFF85FF30.pdf"},"width":1920,"height":1080}},"events":[{"effects":[{"beginTime":0,"baseLayer":{"animations":[],"initialState":{"affineTransform":[1,0,0,1,0,0],"masksToBounds":false,"rotation":0,"scale":1,"position":{"pointX":960,"pointY":540},"width":1920,"sublayerTransform":[1,0,0,0,0,1,0,0,0,0,1,0,0,0,0,1],"contentsRect":{"y":0,"x":0,"width":1,"height":1},"opacity":1,"edgeAntialiasingMask":251658240,"height":1080,"hidden":false,"anchorPoint":{"pointX":0.5,"pointY":0.5}},"objectID":"0","layers":[{"animations":[],"initialState":{"affineTransform":[1,0,0,1,0,0],"masksToBounds":false,"rotation":0,"scale":1,"position":{"pointX":960,"pointY":540},"width":1920,"sublayerTransform":[1,0,0,0,0,1,0,0,0,0,1,-0.00035007912466775983,0,0,0,1],"contentsRect":{"y":0,"x":0,"width":1,"height":1},"opacity":1,"edgeAntialiasingMask":251658240,"height":1080,"hidden":false,"anchorPoint":{"pointX":0.5,"pointY":0.5}},"layers":[{"animations":[],"layers":[],"texturedRectangle":{"isBackgroundTexture":false,"singleTextureOpacity":1,"textureType":0,"textBaseline":0,"textXHeight":0,"isVerticalText":false},"initialState":{"affineTransform":[1,0,0,1,0,0],"masksToBounds":false,"rotation":0,"scale":1,"position":{"pointX":960,"pointY":540},"width":1920,"sublayerTransform":[1,0,0,0,0,1,0,0,0,0,1,0,0,0,0,1],"contentsRect":{"y":0,"x":0,"width":1,"height":1},"opacity":1,"edgeAntialiasingMask":0,"height":1080,"hidden":false,"anchorPoint":{"pointX":0.5,"pointY":0.5}},"texture":"9FEB16CCE631A41FF8DF9B2FBC2D9287"},{"animations":[{"additive":false,"timeOffset":0,"beginTime":0,"from":{"scalar":false},"repeatCount":0,"fillMode":"both","duration":0.01,"autoreverses":false,"property":"hidden","to":{"scalar":true},"removedOnCompletion":false}],"layers":[],"texturedRectangle":{"isBackgroundTexture":false,"singleTextureOpacity":1,"textureType":0,"textBaseline":0,"textXHeight":0,"isVerticalText":false},"initialState":{"affineTransform":[1,0,0,1,0,0],"masksToBounds":false,"rotation":0,"scale":1,"position":{"pointX":960,"pointY":540},"width":1920,"sublayerTransform":[1,0,0,0,0,1,0,0,0,0,1,0,0,0,0,1],"contentsRect":{"y":0,"x":0,"width":1,"height":1},"opacity":1,"edgeAntialiasingMask":0,"height":1080,"hidden":false,"anchorPoint":{"pointX":0.5,"pointY":0.5}},"texture":"67DAA57F27CAEFA2158408D0F5F1A880"}]}]},"effects":[],"duration":0.01,"type":"transition","attributes":{"direction":0},"name":"none","objectID":"0"}],"automaticPlay":false,"hyperlinks":[],"accessibility":[{"text":"The BitMEX trading platform represents the cornerstone of 100x. As the world's most advanced peer-to-peer crypto-products trading platform and API, BitMEX provides knowledge, confidence, and precision to hundreds of thousands of traders, transacting billions of USD per day.","targetRectangle":{"y":248.18776416778564,"x":1271.993408203125,"width":399.54599999999982,"height":260.86724853515625}},{"text":"One of the key drivers for BitMEX’s success is its user experience. Traders from the traditional finance background find a familiar and engaging experience on BitMEX. The UX team’s charter was to build on this theme of necessary complexity and create the best experiences for BitMEX’s customers.","targetRectangle":{"y":552.53288745880127,"x":1271.993408203125,"width":407.82600000000002,"height":260.86724853515625}},{"text":"The phenomenal success of BitMEX’s user experience  set the standard for all cryptocurrency exchanges. ","targetRectangle":{"y":856.87801074981689,"x":1271.993408203125,"width":378.66599999999994,"height":130.43362426757812}},{"text":"http:\/\/udays.xyz","targetRectangle":{"y":1057.8920910358429,"x":1809.7152099609375,"width":101.28515625,"height":15}},{"text":"Portfolio 2018-2021","targetRectangle":{"y":1057.8920910358429,"x":9.1512458324432373,"width":120.146484375,"height":15}},{"text":"pasted-image.tiff","targetRectangle":{"y":133.25527572631836,"x":1365.1972789764404,"width":217.34230041503906,"height":34.236221313476562}},{"text":"pasted-image.tiff","targetRectangle":{"y":7.4607944488525355,"x":1849.7833385467532,"width":42.603643422201003,"height":34.25}},{"text":"Screen Shot 2021-04-16 at 1.03.58 AM.png","targetRectangle":{"y":89.953346252441406,"x":174.78704071044922,"width":648.7313232421875,"height":380.84005737304688}},{"text":"pasted-image.tiff","targetRectangle":{"y":600.7093505859375,"x":-7.1855511665344238,"width":1000.0000000000001,"height":329.184814453125}}],"baseLayer":{"animations":[],"initialState":{"affineTransform":[1,0,0,1,0,0],"masksToBounds":false,"rotation":0,"scale":1,"position":{"pointX":960,"pointY":540},"width":1920,"sublayerTransform":[1,0,0,0,0,1,0,0,0,0,1,0,0,0,0,1],"contentsRect":{"y":0,"x":0,"width":1,"height":1},"opacity":1,"edgeAntialiasingMask":251658240,"height":1080,"hidden":false,"anchorPoint":{"pointX":0.5,"pointY":0.5}},"objectID":"0","layers":[{"animations":[],"initialState":{"affineTransform":[1,0,0,1,0,0],"masksToBounds":false,"rotation":0,"scale":1,"position":{"pointX":960,"pointY":540},"width":1920,"sublayerTransform":[1,0,0,0,0,1,0,0,0,0,1,-0.00035007912466775983,0,0,0,1],"contentsRect":{"y":0,"x":0,"width":1,"height":1},"opacity":1,"edgeAntialiasingMask":251658240,"height":1080,"hidden":false,"anchorPoint":{"pointX":0.5,"pointY":0.5}},"layers":[{"animations":[],"layers":[],"texturedRectangle":{"isBackgroundTexture":false,"singleTextureOpacity":1,"textureType":0,"textBaseline":0,"textXHeight":0,"isVerticalText":false},"initialState":{"affineTransform":[1,0,0,1,0,0],"masksToBounds":false,"rotation":0,"scale":1,"position":{"pointX":960,"pointY":540},"width":1920,"sublayerTransform":[1,0,0,0,0,1,0,0,0,0,1,0,0,0,0,1],"contentsRect":{"y":0,"x":0,"width":1,"height":1},"opacity":1,"edgeAntialiasingMask":0,"height":1080,"hidden":false,"anchorPoint":{"pointX":0.5,"pointY":0.5}},"texture":"67DAA57F27CAEFA2158408D0F5F1A880"}]}]}}]}